{
	"encode": {
		"A":[1,0,0,0,0],
		"B":[0,1,0,0,0],
		"C":[0,0,1,0,0],
		"D":[0,0,0,1,0],
		"E":[0,0,0,0,1]
	},
	"rules": {
		"A":{
			"delay":5,
			"A":"B",
			"B":"C",
			"C":"D",
			"D":"E",
			"E":"A"
		}, 
		"B":{
			"delay":5,
			"A":"B",
			"B":"C",
			"C":"D",
			"D":"E",
			"E":"A"
		},
		"C":{
			"delay":5,
			"A":"B",
			"B":"C",
			"C":"D",
			"D":"E",
			"E":"A"
		},
		"D":{
			"delay":5,
			"A":"B",
			"B":"C",
			"C":"D",
			"D":"E",
			"E":"A"
		},
		"E":{
			"delay":1,
			"A":"B",
			"B":"C",
			"C":"D",
			"D":"E",
			"E":"A"
		}
	}
}
